napari_trackastra/__init__.py
napari_trackastra/_sample_data.py
napari_trackastra/_version.py
napari_trackastra/_widget.py
napari_trackastra/napari.yaml
napari_trackastra/_tests/__init__.py
napari_trackastra/_tests/test_demo_widget.py
napari_trackastra/resources/icon.png
napari_trackastra/resources/trackastra_logo_small.png
napari_trackastra-0.2.1.dist-info/licenses/LICENSE
napari_trackastra-0.2.1.dist-info/METADATA
napari_trackastra-0.2.1.dist-info/WHEEL
napari_trackastra-0.2.1.dist-info/entry_points.txt
napari_trackastra-0.2.1.dist-info/top_level.txt
napari_trackastra-0.2.1.dist-info/RECORD
