Metadata-Version: 2.4
Name: napari-trackastra
Version: 0.2.1
Summary: Napari plugin for cell tracking with trackastra.
Author: Benjamin Gallusser, Martin Weigert
Author-email: bgallusser@gmail.com, marweigert@gmail.com
License: 
Project-URL: Bug Tracker, https://github.com/weigertlab/napari-trackastra/issues
Project-URL: Documentation, https://github.com/weigertlab/napari-trackastra#README.md
Project-URL: Source Code, https://github.com/weigertlab/napari-trackastra
Project-URL: User Support, https://github.com/weigertlab/napari-trackastra/issues
Classifier: Development Status :: 3 - Alpha
Classifier: Framework :: napari
Classifier: Intended Audience :: Developers
Classifier: License :: OSI Approved :: BSD License
Classifier: Operating System :: OS Independent
Classifier: Programming Language :: Python :: 3.10
Classifier: Programming Language :: Python :: 3.11
Classifier: Programming Language :: Python :: 3.12
Classifier: Topic :: Scientific/Engineering :: Image Processing
Requires-Python: >=3.10
License-File: LICENSE
Requires-Dist: numpy
Requires-Dist: scikit-image
Requires-Dist: trackastra>=0.4.1
Requires-Dist: napari-ctc-io
Requires-Dist: napari-geff>=0.0.3
Provides-Extra: testing
Requires-Dist: tox; extra == "testing"
Requires-Dist: pytest; extra == "testing"
Requires-Dist: pytest-cov; extra == "testing"
Requires-Dist: pytest-qt; extra == "testing"
Requires-Dist: napari; extra == "testing"
Requires-Dist: pyqt5; extra == "testing"
Dynamic: license-file
